nrel/routee/powertrain/__about__.py
nrel/routee/powertrain/__init__.py
nrel/routee/powertrain/py.typed
nrel/routee/powertrain/core/__init__.py
nrel/routee/powertrain/core/features.py
nrel/routee/powertrain/core/metadata.py
nrel/routee/powertrain/core/model.py
nrel/routee/powertrain/core/model_config.py
nrel/routee/powertrain/core/powertrain_type.py
nrel/routee/powertrain/core/real_world_adjustments.py
nrel/routee/powertrain/estimators/__init__.py
nrel/routee/powertrain/estimators/estimator_interface.py
nrel/routee/powertrain/estimators/ngboost_estimator.py
nrel/routee/powertrain/estimators/onnx.py
nrel/routee/powertrain/estimators/smart_core.py
nrel/routee/powertrain/estimators/sklearn/__init__.py
nrel/routee/powertrain/estimators/sklearn/estimator.py
nrel/routee/powertrain/estimators/sklearn/port_to_c.py
nrel/routee/powertrain/estimators/sklearn/utils.py
nrel/routee/powertrain/io/__init__.py
nrel/routee/powertrain/io/load.py
nrel/routee/powertrain/io/to_lookup_table.py
nrel/routee/powertrain/resources/__init__.py
nrel/routee/powertrain/resources/default_models/2016_TOYOTA_Camry_4cyl_2WD.json
nrel/routee/powertrain/resources/default_models/2017_CHEVROLET_Bolt.json
nrel/routee/powertrain/resources/default_models/__init__.py
nrel/routee/powertrain/resources/default_models/external_model_links.json
nrel/routee/powertrain/resources/sample_routes/__init__.py
nrel/routee/powertrain/resources/sample_routes/sample_route.csv
nrel/routee/powertrain/trainers/__init__.py
nrel/routee/powertrain/trainers/ngboost_trainer.py
nrel/routee/powertrain/trainers/sklearn_random_forest.py
nrel/routee/powertrain/trainers/smartcore_random_forest.py
nrel/routee/powertrain/trainers/trainer.py
nrel/routee/powertrain/trainers/utils.py
nrel/routee/powertrain/utils/__init__.py
nrel/routee/powertrain/utils/fs.py
nrel/routee/powertrain/validation/__init__.py
nrel/routee/powertrain/validation/errors.py
nrel/routee/powertrain/validation/feature_visualization.py
nrel_routee_powertrain-1.4.0.dist-info/METADATA
nrel_routee_powertrain-1.4.0.dist-info/WHEEL
nrel_routee_powertrain-1.4.0.dist-info/licenses/LICENSE
nrel_routee_powertrain-1.4.0.dist-info/RECORD
