Metadata-Version: 2.4
Name: nrel.routee.powertrain
Version: 1.4.0
Summary: RouteE-Powertrain is a tool for predicting energy usage over a set of road links.
Project-URL: Homepage, https://github.com/NREL/routee-powertrain
Author: National Renewable Energy Laboratory
License: BSD 3-Clause License Copyright (c) 2023, Alliance for Sustainable Energy, LLC
License-File: LICENSE
Classifier: Development Status :: 3 - Alpha
Classifier: Intended Audience :: Science/Research
Classifier: License :: Other/Proprietary License
Classifier: Operating System :: OS Independent
Classifier: Programming Language :: Python
Classifier: Topic :: Scientific/Engineering
Requires-Python: <3.13,>=3.10
Requires-Dist: numpy<3.0,>=2.0
Requires-Dist: onnx<2.0,>=1.17
Requires-Dist: onnxruntime<2.0,>=1.18.1
Requires-Dist: pandas<3.0,>=2.2
Provides-Extra: dev
Requires-Dist: boxsdk; extra == 'dev'
Requires-Dist: hatch; extra == 'dev'
Requires-Dist: jupyter-book; extra == 'dev'
Requires-Dist: matplotlib; extra == 'dev'
Requires-Dist: maturin; extra == 'dev'
Requires-Dist: mypy; extra == 'dev'
Requires-Dist: ngboost==0.5.2; extra == 'dev'
Requires-Dist: pandas-stubs; extra == 'dev'
Requires-Dist: pytest; extra == 'dev'
Requires-Dist: ruff; extra == 'dev'
Requires-Dist: scikit-learn==1.6.1; extra == 'dev'
Requires-Dist: shapely; extra == 'dev'
Requires-Dist: skl2onnx<1.20,>=1.19.1; extra == 'dev'
Requires-Dist: sphinx-book-theme; extra == 'dev'
Requires-Dist: tqdm; extra == 'dev'
Requires-Dist: types-protobuf; extra == 'dev'
Requires-Dist: types-python-dateutil; extra == 'dev'
Requires-Dist: types-pyyaml; extra == 'dev'
Requires-Dist: types-redis; extra == 'dev'
Requires-Dist: types-requests; extra == 'dev'
Provides-Extra: ngboost
Requires-Dist: ngboost==0.5.2; extra == 'ngboost'
Requires-Dist: scikit-learn==1.6.1; extra == 'ngboost'
Provides-Extra: plot
Requires-Dist: matplotlib; extra == 'plot'
Provides-Extra: scikit
Requires-Dist: scikit-learn==1.6.1; extra == 'scikit'
Requires-Dist: skl2onnx<1.20,>=1.19.1; extra == 'scikit'
